resmo/__init__.py
resmo/generate_modified_data.py
resmo/util.py
resmo/modification/__init__.py
resmo/modification/mask_residue.py
resmo/modification/modification.py
resmo/modification/signature.py
resmo/protein_model/__init__.py
resmo/protein_model/base.py
resmo/protein_model/mol2.py
resmo-0.0.7.dist-info/METADATA
resmo-0.0.7.dist-info/WHEEL
resmo-0.0.7.dist-info/top_level.txt
resmo-0.0.7.dist-info/RECORD
